KratosMultiphysics/IgaApplication/__init__.py
KratosMultiphysics/IgaApplication/assign_iga_external_conditions_process.py
KratosMultiphysics/IgaApplication/assign_integration_points_to_background_elements_process.py
KratosMultiphysics/IgaApplication/assign_vector_variable_and_constraints_to_conditions_process.py
KratosMultiphysics/IgaApplication/iga_output_process.py
KratosMultiphysics/IgaApplication/kratos_main_iga.py
KratosMultiphysics/IgaApplication/map_nurbs_volume_results_to_embedded_geometry_process.py
KratosMultiphysics/IgaApplication/nitsche_stabilization_process.py
KratosMultiphysics/IgaApplication/output_eigen_values_process.py
KratosMultiphysics/IgaApplication/output_quadrature_domain_process.py
KratosMultiphysics/IgaApplication/set_directors_process.py
KratosMultiphysics/IgaApplication/vtk_embedded_geometry_output_process.py
KratosMultiphysics/.libs/KratosIgaApplication.cpython-39-x86_64-linux-gnu.so
KratosMultiphysics/.libs/libKratosIgaCore.so
kratosigaapplication-10.4.0.dist-info/METADATA
kratosigaapplication-10.4.0.dist-info/WHEEL
kratosigaapplication-10.4.0.dist-info/RECORD
